craftpainting/__init__.py
craftpainting/__main__.py
craftpainting/enlarge.py
craftpainting/painting.py
craftpainting-0.0.3.dist-info/METADATA
craftpainting-0.0.3.dist-info/WHEEL
craftpainting-0.0.3.dist-info/entry_points.txt
craftpainting-0.0.3.dist-info/top_level.txt
craftpainting-0.0.3.dist-info/RECORD
