Metadata-Version: 2.1
Name: craftpainting
Version: 0.0.3
Summary: Create Minecraft-like paintings
Home-page: https://github.com/ninest/craftpainting
License: MIT
Project-URL: Bug Tracker, https://github.com/ninest/craftpainting/issues
Project-URL: Documentation, https://github.com/ninest/craftpainting
Project-URL: Source Code, https://github.com/ninest/craftpainting
Platform: UNKNOWN
